MANIFEST.in
setup.cfg
setup.py
plymgf/__init__.py
plymgf/classlexer.py
plymgf/lextab.py
plymgf/mgfreader.py
plymgf/test_classlexer.py
plymgf.egg-info/PKG-INFO
plymgf.egg-info/SOURCES.txt
plymgf.egg-info/dependency_links.txt
plymgf.egg-info/requires.txt
plymgf.egg-info/top_level.txt
plymgf/data/test.mgf