Metadata-Version: 1.1
Name: plymgf
Version: 0.2.8
Summary: A MGF files reader with PLY
Home-page: https://github.com/Astyan-42/plymgf
Author: Astyan
Author-email: aurelien.vezin.dev@gmail.com
License: CeCILL-B
Keywords: mgf,parser,reader
Platform: UNKNOWN
Classifier: Development Status :: 4 - Beta
Classifier: Intended Audience :: Developers
Classifier: Topic :: Software Development :: Libraries :: Python Modules
Classifier: License :: OSI Approved
Classifier: Programming Language :: Python :: 2
Classifier: Programming Language :: Python :: 2.7
Classifier: Programming Language :: Python :: 3
Classifier: Programming Language :: Python :: 3.4
Classifier: Programming Language :: Python :: 3.5
Classifier: Operating System :: OS Independent
